aioxnat/__init__.py
aioxnat/objects.py
aioxnat/protocols.py
aioxnat/rest.py
aioxnat-0.0.5.dist-info/LICENSE.txt
aioxnat-0.0.5.dist-info/METADATA
aioxnat-0.0.5.dist-info/WHEEL
aioxnat-0.0.5.dist-info/top_level.txt
aioxnat-0.0.5.dist-info/RECORD
